syntaxnet-0.2.data/purelib/dragnn/__init__.py
syntaxnet-0.2.data/purelib/dragnn/core/__init__.py
syntaxnet-0.2.data/purelib/dragnn/core/ops/__init__.py
syntaxnet-0.2.data/purelib/dragnn/core/ops/gen_dragnn_bulk_ops.py
syntaxnet-0.2.data/purelib/dragnn/core/ops/gen_dragnn_ops.py
syntaxnet-0.2.data/purelib/dragnn/protos/__init__.py
syntaxnet-0.2.data/purelib/dragnn/protos/data_pb2.py
syntaxnet-0.2.data/purelib/dragnn/protos/spec_pb2.py
syntaxnet-0.2.data/purelib/dragnn/protos/trace_pb2.py
syntaxnet-0.2.data/purelib/dragnn/python/__init__.py
syntaxnet-0.2.data/purelib/dragnn/python/biaffine_units.py
syntaxnet-0.2.data/purelib/dragnn/python/bulk_component.py
syntaxnet-0.2.data/purelib/dragnn/python/component.py
syntaxnet-0.2.data/purelib/dragnn/python/composite_optimizer.py
syntaxnet-0.2.data/purelib/dragnn/python/digraph_ops.py
syntaxnet-0.2.data/purelib/dragnn/python/dragnn_cc_impl.so
syntaxnet-0.2.data/purelib/dragnn/python/dragnn_ops.py
syntaxnet-0.2.data/purelib/dragnn/python/evaluation.py
syntaxnet-0.2.data/purelib/dragnn/python/graph_builder.py
syntaxnet-0.2.data/purelib/dragnn/python/lexicon.py
syntaxnet-0.2.data/purelib/dragnn/python/load_dragnn_cc_impl.py
syntaxnet-0.2.data/purelib/dragnn/python/network_units.py
syntaxnet-0.2.data/purelib/dragnn/python/render_parse_tree_graphviz.py
syntaxnet-0.2.data/purelib/dragnn/python/render_spec_with_graphviz.py
syntaxnet-0.2.data/purelib/dragnn/python/sentence_io.py
syntaxnet-0.2.data/purelib/dragnn/python/spec_builder.py
syntaxnet-0.2.data/purelib/dragnn/python/trainer_lib.py
syntaxnet-0.2.data/purelib/dragnn/python/visualization
syntaxnet-0.2.data/purelib/dragnn/python/visualization.py
syntaxnet-0.2.data/purelib/dragnn/python/wrapped_units.py
syntaxnet-0.2.data/purelib/dragnn/tools/__init__.py
syntaxnet-0.2.data/purelib/dragnn/tools/build_pip_package
syntaxnet-0.2.data/purelib/dragnn/tools/build_pip_package.py
syntaxnet-0.2.data/purelib/dragnn/tools/oss_setup.py
syntaxnet-0.2.dist-info/DESCRIPTION.rst
syntaxnet-0.2.dist-info/METADATA
syntaxnet-0.2.dist-info/RECORD
syntaxnet-0.2.dist-info/WHEEL
syntaxnet-0.2.dist-info/metadata.json
syntaxnet-0.2.dist-info/top_level.txt
