Metadata-Version: 2.0
Name: syntaxnet
Version: 0.2
Summary: SyntaxNet: Neural Models of Syntax
Home-page: https://github.com/tensorflow/models/tree/master/syntaxnet
Author: Google Inc.
Author-email: opensource@google.com
License: Apache 2.0
Keywords: syntaxnet machine learning
Platform: UNKNOWN
Classifier: Intended Audience :: Developers
Classifier: Intended Audience :: Education
Classifier: Intended Audience :: Science/Research
Classifier: License :: OSI Approved :: Apache Software License
Classifier: Programming Language :: Python :: 2.7
Classifier: Topic :: Scientific/Engineering :: Mathematics
Requires-Dist: pygraphviz
Requires-Dist: tensorflow
